webhooks_automata/__init__.py
webhooks_automata/app.py
webhooks_automata/settings.py
webhooks_automata/scripts/__init__.py
webhooks_automata/union_models/__init__.py
webhooks_automata/union_models/actions.py
webhooks_automata/union_models/endpoints.py
webhooks_automata-0.2.0.dist-info/METADATA
webhooks_automata-0.2.0.dist-info/WHEEL
webhooks_automata-0.2.0.dist-info/entry_points.txt
webhooks_automata-0.2.0.dist-info/licenses/LICENSE
webhooks_automata-0.2.0.dist-info/RECORD
