Metadata-Version: 2.1
Name: webhooks-automata
Version: 0.2.0
Summary: Webhook receiver for flexible automations
Project-URL: Source code, https://github.com/alexbarcelo/webhooks-automata
Author-email: Alex Barcelo <alex@betarho.net>
License-Expression: Apache-2.0
License-File: LICENSE
Classifier: License :: OSI Approved :: Apache Software License
Classifier: Operating System :: OS Independent
Classifier: Programming Language :: Python :: 3
Requires-Python: >=3.11
Requires-Dist: click
Requires-Dist: pydantic>=2.0
Requires-Dist: pyyaml>=6.0.1
Requires-Dist: starlette
Requires-Dist: uvicorn
